{"Partnership": "", "Corporation": "", "Telephone Number": "", "Employer": "Harp&Callier/Law Office of JA Harp", "Individual": "", "Address in Item 4": "", "Date": "02/25/13", "Address in Item 5": "", "State": "", "Address in Item 3": "", "Month/Day/Year (mm/dd/yyyy)": "12/31/2013", "ZIP Code + 4": "30240", "Organization": "The Callier Firm", "Street": "", "Signed": "Astap other (Specify)", "Name": "R", "P.O. Box, Bldg., Room No., if any": "Suite 210", "City": "", "1. File Number E-": "6160", "Title": "!", "Other (specify) 1/2 year partnership/1/2 year sole owi": "X", "Trade Name": "", "Attention To": "", "2. Fiscal Year Covered": "From:", "14. Signed": "", "Expires": "08-31-2016", "No.": "1245-0003", "NO": "X", "YES": "", "File Number E-": "", "8. Type of Reportable Activity Engaged In By Employer": "Read the following questions and the accompanying instructions carefully, taking into consideration the exclusions listed the instructions for these items, and check either \"Yes\" or \"No\" for each item. For each item that is answered \"Yes\", you attach a Part B which appears on Page 3. Complete a separate Part B for each \"Yes\" answer to any of Items 8.a. through Also, if the answer is \"Yes\" for more than one person or organization, complete a separate Part B for each person or organization. If you answer \"Yes\", enter the number of Part Bs that are submitted for that item in the line indicated.", "Name of Reporting Employer": "", "Both": "", "Written*": "", "Oral": "X", "Agreement": "", "Payment": "X", "ITEM 8.b": "", "ITEM 8.c": "", "ITEM 8.a": "X", "9.c. Position In labor organization or with employer (if an independent labor consultant, so state).": "Local Chairman", "10.a. Date of the promise, agreement, or arrangement pursuant to which payments or expenditures were agreed to or made.": "2/25/2013", "ITEM 8.d": "", "11.a. Date of each payment or expenditure ( mm/dd/yyyy ).": "2/25/21013", "ITEM 8.e": "", "ITEM 8.f": "", "11.b. Amount of each payment or expenditure": "$1062", "Payment to Pebblebrook Restaurant for thirty meal": "", "Grand Total": "$1,062.00", "Invoice #": "22513.1", "Subtotal": "$ 900.00", "Account": "Harp & Callier, LLP", "18% Gratuity": "$ 162.00", "Tax": "$ -", "Price": "$30.00"}